gates/transmission_gate.v
module transmission_gates();
// variables resistive bi-directional gates
//syntax:


reg data_low, in; 
wire data_bus, out1, out2;

//keyword name(inout, inout, control)
/*

bifif0
tristate buffer, active low energy
 Basically if data_low is on, data_bus has impedence (Z)
 and current can't pass through. 
 if data_low if off
 current from in, reaches data_bus

bufif1
If data_low is on, then "in " can turn data_bus on
*/
notif0 U1(data_bus, in, data_low);
//buff out1 is on, if in is on 
buf U2(out1, in);
// inverse of buff
not U3(out2, in);
initial begin 
    $dumpfile("transmission.vcd");
    $dumpvars();
    $monitor ("@%g in=%b data_enable_low=%b out1=%b out2= b data_bus=%b", 
        $time, in, data_low, out1, out2, data_bus);
    
    data_low =0;
    in=0;
    #4 data_low = 1;
    #4 data_low = 0;
    #8 $finish;


end 

always #2 in=~in;
endmodule

gates/transmission.vcd
$date
	Sun Aug 13 11:05:36 2023
$end
$version
	Icarus Verilog
$end
$timescale
	1s
$end
$scope module transmission_gates $end
$var wire 1 ! data_bus $end
$var wire 1 " out1 $end
$var wire 1 # out2 $end
$var reg 1 $ data_low $end
$var reg 1 % in $end
$upscope $end
$enddefinitions $end
$comment Show the parameter values. $end
$dumpall
$end
#0
$dumpvars
0%
0$
1#
0"
1!
$end
#2
0#
1"
0!
1%
#4
1#
0"
0%
z!
1$
#6
0#
1"
1%
#8
1#
0"
0%
1!
0$
#10
0#
1"
0!
1%
#12
1#
0"
1!
0%
#14
0#
1"
0!
1%
#16
1#
0"
1!
0%
