counters/divide_by_4-5_counter/divide_by_4_5_counter.v
module counter_4_5(
    input clk_in,
    input reset,
    // input enable,
    output clk_out
);

reg [3:0] pos_edge;
reg [3:0] neg_edge;
reg toggle;
reg toggle1;

always @ (posedge clk_in)
    if (reset ==1) begin
        pos_edge <= 0;
        neg_edge <= 0;
    end
    else begin
        pos_edge <=  pos_edge +1;
    end 

always @(negedge clk_in)
    if (reset ==1) begin
        pos_edge <= 0;
        neg_edge <= 0;
    end
    else if (neg_edge == 4)begin
        neg_edge <=0;
        pos_edge <=0;
    end else begin
        neg_edge <=  neg_edge +1;
    end 


assign clk_out  = neg_edge < 4  &&  pos_edge >= 1;
endmodule 

module tb();

reg clk_in;
reg reset;
wire clk_out;
counter_4_5 U(
    clk_in,
    reset,
    clk_out
);
initial begin
    clk_in = 0;
    reset = 0;
    $dumpfile("divide_45.vcd");
    $dumpvars();
    #2 reset = 1;
    #10 reset = 10;
    #100 $finish;
end

always  #1  clk_in =~ clk_in;
endmodule

counters/divide_by_4-5_counter/divide_45.vcd
$date
	Tue Aug 15 21:47:56 2023
$end
$version
	Icarus Verilog
$end
$timescale
	1s
$end
$scope module tb $end
$var wire 1 ! clk_out $end
$var reg 1 " clk_in $end
$var reg 1 # reset $end
$scope module U $end
$var wire 1 " clk_in $end
$var wire 1 ! clk_out $end
$var wire 1 # reset $end
$var reg 4 $ neg_edge [3:0] $end
$var reg 4 % pos_edge [3:0] $end
$upscope $end
$upscope $end
$enddefinitions $end
$comment Show the parameter values. $end
$dumpall
$end
#0
$dumpvars
bx %
bx $
0#
0"
x!
$end
#1
1"
#2
0!
b0 $
b0 %
0"
1#
#3
1"
#4
0"
#5
1"
#6
0"
#7
1"
#8
0"
#9
1"
#10
0"
#11
1"
#12
b1 $
0"
0#
#13
1!
b1 %
1"
#14
b10 $
0"
#15
b10 %
1"
#16
b11 $
0"
#17
b11 %
1"
#18
0!
b100 $
0"
#19
b100 %
1"
#20
b0 %
b0 $
0"
#21
1!
b1 %
1"
#22
b1 $
0"
#23
b10 %
1"
#24
b10 $
0"
#25
b11 %
1"
#26
b11 $
0"
#27
b100 %
1"
#28
0!
b100 $
0"
#29
b101 %
1"
#30
b0 %
b0 $
0"
#31
1!
b1 %
1"
#32
b1 $
0"
#33
b10 %
1"
#34
b10 $
0"
#35
b11 %
1"
#36
b11 $
0"
#37
b100 %
1"
#38
0!
b100 $
0"
#39
b101 %
1"
#40
b0 %
b0 $
0"
#41
1!
b1 %
1"
#42
b1 $
0"
#43
b10 %
1"
#44
b10 $
0"
#45
b11 %
1"
#46
b11 $
0"
#47
b100 %
1"
#48
0!
b100 $
0"
#49
b101 %
1"
#50
b0 %
b0 $
0"
#51
1!
b1 %
1"
#52
b1 $
0"
#53
b10 %
1"
#54
b10 $
0"
#55
b11 %
1"
#56
b11 $
0"
#57
b100 %
1"
#58
0!
b100 $
0"
#59
b101 %
1"
#60
b0 %
b0 $
0"
#61
1!
b1 %
1"
#62
b1 $
0"
#63
b10 %
1"
#64
b10 $
0"
#65
b11 %
1"
#66
b11 $
0"
#67
b100 %
1"
#68
0!
b100 $
0"
#69
b101 %
1"
#70
b0 %
b0 $
0"
#71
1!
b1 %
1"
#72
b1 $
0"
#73
b10 %
1"
#74
b10 $
0"
#75
b11 %
1"
#76
b11 $
0"
#77
b100 %
1"
#78
0!
b100 $
0"
#79
b101 %
1"
#80
b0 %
b0 $
0"
#81
1!
b1 %
1"
#82
b1 $
0"
#83
b10 %
1"
#84
b10 $
0"
#85
b11 %
1"
#86
b11 $
0"
#87
b100 %
1"
#88
0!
b100 $
0"
#89
b101 %
1"
#90
b0 %
b0 $
0"
#91
1!
b1 %
1"
#92
b1 $
0"
#93
b10 %
1"
#94
b10 $
0"
#95
b11 %
1"
#96
b11 $
0"
#97
b100 %
1"
#98
0!
b100 $
0"
#99
b101 %
1"
#100
b0 %
b0 $
0"
#101
1!
b1 %
1"
#102
b1 $
0"
#103
b10 %
1"
#104
b10 $
0"
#105
b11 %
1"
#106
b11 $
0"
#107
b100 %
1"
#108
0!
b100 $
0"
#109
b101 %
1"
#110
b0 %
b0 $
0"
#111
1!
b1 %
1"
#112
b1 $
0"
