counters/divide_by_5_counter/divide5.v
module divide_5(
    input clk_in,
    input reset,
    output clk_out
);

wire clk_in, reset, clk_out;

reg [2:0] pos_cnt;
reg [2:0] neg_cnt;

always @(posedge clk_in)
    begin
        if (reset) begin 
            pos_cnt <=0;
        end 
        else begin
            pos_cnt = pos_cnt == 5 ? 0: pos_cnt +1;
        end 
        
    end 

always @(negedge clk_in)
    begin
        if (reset) begin 
            neg_cnt <=0;
        end 
        else begin
        neg_cnt = neg_cnt==5 ? 0 : neg_cnt +1;
        end 
    end 


assign clk_out =  pos_cnt != 5; // && neg_cnt != 5;
endmodule

module test();
wire clk_out;
reg  reset, clk_in;
divide_5 U(
    clk_in,
    reset,
    clk_out
);
initial begin
    $dumpfile("divide5_tb.vcd");
    $dumpvars();
    clk_in = 0;
    #1 reset = 1;
    
    #5 reset = 0;
    #100 $finish;

end
always #1 clk_in =~clk_in;

endmodule

counters/divide_by_5_counter/divide5_tb.vcd
$date
	Tue Aug 15 20:02:35 2023
$end
$version
	Icarus Verilog
$end
$timescale
	1s
$end
$scope module test $end
$var wire 1 ! clk_out $end
$var reg 1 " clk_in $end
$var reg 1 # reset $end
$scope module U $end
$var wire 1 " clk_in $end
$var wire 1 # reset $end
$var wire 1 ! clk_out $end
$var reg 3 $ neg_cnt [2:0] $end
$var reg 3 % pos_cnt [2:0] $end
$upscope $end
$upscope $end
$enddefinitions $end
$comment Show the parameter values. $end
$dumpall
$end
#0
$dumpvars
bx %
bx $
x#
0"
x!
$end
#1
1!
b0 %
1"
1#
#2
b0 $
0"
#3
1"
#4
0"
#5
1"
#6
b1 $
0"
0#
#7
b1 %
1"
#8
b10 $
0"
#9
b10 %
1"
#10
b11 $
0"
#11
b11 %
1"
#12
b100 $
0"
#13
b100 %
1"
#14
b101 $
0"
#15
0!
b101 %
1"
#16
b0 $
0"
#17
1!
b0 %
1"
#18
b1 $
0"
#19
b1 %
1"
#20
b10 $
0"
#21
b10 %
1"
#22
b11 $
0"
#23
b11 %
1"
#24
b100 $
0"
#25
b100 %
1"
#26
b101 $
0"
#27
0!
b101 %
1"
#28
b0 $
0"
#29
1!
b0 %
1"
#30
b1 $
0"
#31
b1 %
1"
#32
b10 $
0"
#33
b10 %
1"
#34
b11 $
0"
#35
b11 %
1"
#36
b100 $
0"
#37
b100 %
1"
#38
b101 $
0"
#39
0!
b101 %
1"
#40
b0 $
0"
#41
1!
b0 %
1"
#42
b1 $
0"
#43
b1 %
1"
#44
b10 $
0"
#45
b10 %
1"
#46
b11 $
0"
#47
b11 %
1"
#48
b100 $
0"
#49
b100 %
1"
#50
b101 $
0"
#51
0!
b101 %
1"
#52
b0 $
0"
#53
1!
b0 %
1"
#54
b1 $
0"
#55
b1 %
1"
#56
b10 $
0"
#57
b10 %
1"
#58
b11 $
0"
#59
b11 %
1"
#60
b100 $
0"
#61
b100 %
1"
#62
b101 $
0"
#63
0!
b101 %
1"
#64
b0 $
0"
#65
1!
b0 %
1"
#66
b1 $
0"
#67
b1 %
1"
#68
b10 $
0"
#69
b10 %
1"
#70
b11 $
0"
#71
b11 %
1"
#72
b100 $
0"
#73
b100 %
1"
#74
b101 $
0"
#75
0!
b101 %
1"
#76
b0 $
0"
#77
1!
b0 %
1"
#78
b1 $
0"
#79
b1 %
1"
#80
b10 $
0"
#81
b10 %
1"
#82
b11 $
0"
#83
b11 %
1"
#84
b100 $
0"
#85
b100 %
1"
#86
b101 $
0"
#87
0!
b101 %
1"
#88
b0 $
0"
#89
1!
b0 %
1"
#90
b1 $
0"
#91
b1 %
1"
#92
b10 $
0"
#93
b10 %
1"
#94
b11 $
0"
#95
b11 %
1"
#96
b100 $
0"
#97
b100 %
1"
#98
b101 $
0"
#99
0!
b101 %
1"
#100
b0 $
0"
#101
1!
b0 %
1"
#102
b1 $
0"
#103
b1 %
1"
#104
b10 $
0"
#105
b10 %
1"
#106
b11 $
0"
