UART_Transmitter/transmitter.v
// 4 bit transmitter with 1 start and 1 stop bit
module transmitter(
    input wire receiver_clk,
    
    input wire pin1,
    input wire pin2,
    input wire pin3, 
    input wire pin4,

    output reg transmitter

);
reg [2:0] transmitter_counter = 3'b0 ;
reg [5:0] transmitter_memory  = 6'b0; 

initial begin
    transmitter = 0;
    transmitter_counter = 0;
end 
always @(posedge receiver_clk) 
    if (transmitter_counter != 0) begin
        transmitter_counter <= transmitter_counter - 1; 
        transmitter = transmitter_memory[transmitter_counter -1];
        

    end else if (transmitter_counter == 0) begin 
        transmitter <= 0;
        transmitter_counter <= 6;
        transmitter_memory <= {1'b1, pin1, pin2, pin3, pin4, 1'b1};
    end 
endmodule 

// Just pretend like the clock I'm inputting here is synced up to the BaudRate_generator clock
module test_transmitter();
reg receiver_clk;
reg pin1, pin2, pin3, pin4; 
wire transmitter;
reg counter;
transmitter U(
    .receiver_clk(receiver_clk),
    .pin1(pin1),
    .pin2(pin2),
    .pin3(pin3),
    .pin4(pin4),
    .transmitter(transmitter)
);

initial begin
    $dumpfile("UART_Transmitter.vcd");
    $dumpvars();
    receiver_clk = 0;
    pin1 = 0;
    pin2 = 0;
    pin3 = 0;
    pin4 = 0;
    #1
    pin1 = 1;
    pin2 = 0;
    pin3 = 1;
    pin4 = 1;
    #1
    pin1 = 0;
    pin2 = 0;
    pin3 = 0;
    pin4 = 0;
    #13
    pin1 = 1;
    pin2 = 1;
    pin3 = 0;
    pin4 = 1;
    #1
    pin1 = 0;
    pin2 = 0;
    pin3 = 0;
    pin4 = 0;
    #13
    pin1 = 1;
    pin2 = 1;
    pin3 = 0;
    pin4 = 1;
    #1
    pin1 = 0;
    pin2 = 0;
    pin3 = 0;
    pin4 = 0;
    #13
    pin1 = 1;
    pin2 = 1;
    pin3 = 0;
    pin4 = 1;
    #1
    pin1 = 0;
    pin2 = 0;
    pin3 = 0;
    pin4 = 0;
    #13
    pin1 = 0;
    pin2 = 1;
    pin3 = 0;
    pin4 = 0;
    #1
    pin1 = 0;
    pin2 = 0;
    pin3 = 0;
    pin4 = 0;
    #40 $finish;

end 
always #1 receiver_clk = ~receiver_clk;
endmodule

UART_Transmitter/UART_Transmitter.vcd
$date
	Sun Aug 20 09:44:56 2023
$end
$version
	Icarus Verilog
$end
$timescale
	1s
$end
$scope module test_transmitter $end
$var wire 1 ! transmitter $end
$var reg 1 " pin1 $end
$var reg 1 # pin2 $end
$var reg 1 $ pin3 $end
$var reg 1 % pin4 $end
$var reg 1 & receiver_clk $end
$scope module U $end
$var wire 1 " pin1 $end
$var wire 1 # pin2 $end
$var wire 1 $ pin3 $end
$var wire 1 % pin4 $end
$var wire 1 & receiver_clk $end
$var reg 1 ! transmitter $end
$var reg 3 ' transmitter_counter [2:0] $end
$var reg 6 ( transmitter_memory [5:0] $end
$upscope $end
$upscope $end
$enddefinitions $end
$comment Show the parameter values. $end
$dumpall
$end
#0
$dumpvars
b0 (
b0 '
0&
0%
0$
0#
0"
0!
$end
#1
b110111 (
b110 '
1&
1%
1$
1"
#2
0&
0%
0$
0"
#3
b101 '
1!
1&
#4
0&
#5
b100 '
1&
#6
0&
#7
b11 '
0!
1&
#8
0&
#9
b10 '
1!
1&
#10
0&
#11
b1 '
1&
#12
0&
#13
b0 '
1&
#14
0&
#15
b111011 (
b110 '
0!
1&
1%
1#
1"
#16
0&
0%
0#
0"
#17
b101 '
1!
1&
#18
0&
#19
b100 '
1&
#20
0&
#21
b11 '
1&
#22
0&
#23
b10 '
0!
1&
#24
0&
#25
b1 '
1!
1&
#26
0&
#27
b0 '
1&
#28
0&
#29
b110 '
0!
1&
1%
1#
1"
#30
0&
0%
0#
0"
#31
b101 '
1!
1&
#32
0&
#33
b100 '
1&
#34
0&
#35
b11 '
1&
#36
0&
#37
b10 '
0!
1&
#38
0&
#39
b1 '
1!
1&
#40
0&
#41
b0 '
1&
#42
0&
#43
b110 '
0!
1&
1%
1#
1"
#44
0&
0%
0#
0"
#45
b101 '
1!
1&
#46
0&
#47
b100 '
1&
#48
0&
#49
b11 '
1&
#50
0&
#51
b10 '
0!
1&
#52
0&
#53
b1 '
1!
1&
#54
0&
#55
b0 '
1&
#56
0&
#57
b101001 (
b110 '
0!
1&
1#
#58
0&
0#
#59
b101 '
1!
1&
#60
0&
#61
b100 '
0!
1&
#62
0&
#63
b11 '
1!
1&
#64
0&
#65
b10 '
0!
1&
#66
0&
#67
b1 '
1&
#68
0&
#69
b0 '
1!
1&
#70
0&
#71
b100001 (
b110 '
0!
1&
#72
0&
#73
b101 '
1!
1&
#74
0&
#75
b100 '
0!
1&
#76
0&
#77
b11 '
1&
#78
0&
#79
b10 '
1&
#80
0&
#81
b1 '
1&
#82
0&
#83
b0 '
1!
1&
#84
0&
#85
b110 '
0!
1&
#86
0&
#87
b101 '
1!
1&
#88
0&
#89
b100 '
0!
1&
#90
0&
#91
b11 '
1&
#92
0&
#93
b10 '
1&
#94
0&
#95
b1 '
1&
#96
0&
#97
b0 '
1!
1&
