counters/counter/counter.v
module counter(
    clock,
    reset,
    enable,
    counter_out
);
input reset, clock, enable;
// by rule all input ports are wires
wire clock;
wire reset;
wire enable;

// output can be storage element (reg) or wire
// 4 bit output: meaning it is 4 binary position value
output [3:0] counter_out;
reg [3:0] counter_out ; 

always @ (posedge clock)
begin: COUNTER // blockname 

    // `b1 designates binary, and number of bits 
    if (reset == 1'b1) begin
        counter_out <=  #1  4'b0000; 
        /* can't set a value for enable, as 
        wire values can only bet set in the test bench.
        Also on the DUT, the reset wire has no bearing on
        if the enable wire is ON or OFF
        */
        // enable <= 0;

    end 
    else if (enable == 1'b1 ) begin
        counter_out <= #1 counter_out + 1;
    end
end 
endmodule

counters/counter/counter_tb.v
`include "counter.v"
module counter_tb(); 
counter U_counter (
    clock,
    reset,
    enable,
    counter_out
);

// "counter" needs to match up with included filename

// declare inputs as regs, and OUTPUTs as wires
reg clock, reset, enable;
wire [3:0] counter_out;

//built in delays 
// buf #(5) (reset, enable, counter_out)
// or 
// buf #(5, 3) (reset, enable) // you get it
/*
buf #(1,0)U_rise (rise_delay,in); 
 buf #(0,1)U_fall (fall_delay,in); 
 buf  #1  U_all (all_delay,in); 
*/
initial begin 
    $dumpfile("counter.vcd");
    $dumpvars(0,counter_tb);
    $monitor ("%g\t %b   %b     %b      %b",  $time, clock, reset, enable, counter_out);
    $display("Test complete yo");
    clock = 1;
    reset = 0;
    enable = 0;
    #5 reset = 1;
    #10 reset = 0;
    #10 enable = 1;
    #10 enable =0;
    #10 enable = 1;
    #10 enable =0;
    #10 enable = 1;
    #10 enable =0;
    #5 $finish;


end 

//toggle every 5 ticks
always begin
    #5 clock =~ clock;
end
// Connect DUT to test bench

endmodule

counters/counter/counter.vcd
$date
	Mon Aug 14 23:12:46 2023
$end
$version
	Icarus Verilog
$end
$timescale
	1s
$end
$scope module counter_tb $end
$var wire 4 ! counter_out [3:0] $end
$var reg 1 " clock $end
$var reg 1 # enable $end
$var reg 1 $ reset $end
$scope module U_counter $end
$var wire 1 " clock $end
$var wire 1 # enable $end
$var wire 1 $ reset $end
$var reg 4 % counter_out [3:0] $end
$scope begin COUNTER $end
$upscope $end
$upscope $end
$upscope $end
$enddefinitions $end
$comment Show the parameter values. $end
$dumpall
$end
#0
$dumpvars
bx %
0$
0#
1"
bx !
$end
#5
0"
1$
#10
1"
#11
b0 !
b0 %
#15
0"
0$
#20
1"
#25
0"
1#
#30
1"
#31
b1 !
b1 %
#35
0"
0#
#40
1"
#45
0"
1#
#50
1"
#51
b10 !
b10 %
#55
0"
0#
#60
1"
#65
0"
1#
#70
1"
#71
b11 !
b11 %
#75
0"
0#
